{
  "version": "5.8.1",
  "flags": {},
  "shapes": [
    {
      "label": "cannabis",
      "points": [
        [
          74.98310291858678,
          69.89247311827957
        ],
        [
          80.82027649769583,
          70.35330261136713
        ],
        [
          82.81720430107524,
          65.13056835637481
        ],
        [
          85.27496159754222,
          61.136712749615974
        ],
        [
          93.1090629800307,
          58.83256528417819
        ],
        [
          96.64208909370197,
          58.678955453149
        ],
        [
          104.01536098310291,
          64.36251920122888
        ],
        [
          105.85867895545312,
          68.20276497695853
        ],
        [
          113.23195084485405,
          69.73886328725038
        ],
        [
          110.4669738863287,
          75.26881720430107
        ],
        [
          103.55453149001534,
          82.33486943164363
        ],
        [
          123.52380952380949,
          86.9431643625192
        ],
        [
          123.21658986175115,
          120.43010752688173
        ],
        [
          108.77726574500767,
          125.65284178187405
        ],
        [
          98.79262672811058,
          126.42089093701998
        ],
        [
          87.11827956989245,
          119.81566820276498
        ],
        [
          81.2811059907834,
          111.05990783410138
        ],
        [
          74.52227342549921,
          88.63287250384025
        ]
      ],
      "group_id": null,
      "description": "",
      "shape_type": "polygon",
      "flags": {},
      "mask": null
    }
  ],
  "imageData": null,
  "imagePath": "10027019_20160620.tif",
  "imageHeight": 285,
  "imageWidth": 128
}
