{
  "version": "5.8.1",
  "flags": {},
  "shapes": [
    {
      "label": "hoop house",
      "points": [
        [
          37.33660130718954,
          22.22222222222222
        ],
        [
          45.34313725490196,
          21.895424836601308
        ],
        [
          46.65032679738562,
          67.97385620915033
        ],
        [
          38.970588235294116,
          68.30065359477123
        ]
      ],
      "group_id": null,
      "description": "",
      "shape_type": "polygon",
      "flags": {},
      "mask": null
    },
    {
      "label": "hoop house",
      "points": [
        [
          46.97712418300654,
          24.34640522875817
        ],
        [
          54.16666666666667,
          23.856209150326798
        ],
        [
          55.63725490196079,
          67.15686274509804
        ],
        [
          47.467320261437905,
          67.15686274509804
        ]
      ],
      "group_id": null,
      "description": "",
      "shape_type": "polygon",
      "flags": {},
      "mask": null
    },
    {
      "label": "hoop house",
      "points": [
        [
          39.950980392156865,
          78.10457516339869
        ],
        [
          40.9313725490196,
          84.640522875817
        ],
        [
          82.59803921568627,
          76.63398692810458
        ],
        [
          81.29084967320262,
          69.93464052287581
        ]
      ],
      "group_id": null,
      "description": "",
      "shape_type": "polygon",
      "flags": {},
      "mask": null
    },
    {
      "label": "hoop house",
      "points": [
        [
          42.07516339869281,
          91.33986928104575
        ],
        [
          44.035947712418306,
          98.36601307189542
        ],
        [
          86.02941176470588,
          85.94771241830065
        ],
        [
          83.74183006535948,
          79.41176470588235
        ]
      ],
      "group_id": null,
      "description": "",
      "shape_type": "polygon",
      "flags": {},
      "mask": null
    },
    {
      "label": "cannabis",
      "points": [
        [
          44.035947712418306,
          99.50980392156863
        ],
        [
          85.53921568627452,
          88.0718954248366
        ],
        [
          86.02941176470588,
          104.57516339869281
        ],
        [
          63.48039215686275,
          110.7843137254902
        ],
        [
          52.205882352941174,
          109.15032679738562
        ],
        [
          45.66993464052288,
          106.04575163398692
        ]
      ],
      "group_id": null,
      "description": "",
      "shape_type": "polygon",
      "flags": {},
      "mask": null
    }
  ],
  "imagePath": "14011015_20160620.tif",
  "imageHeight": 404,
  "imageWidth": 200
}
