{
  "version": "5.8.1",
  "flags": {},
  "shapes": [
    {
      "label": "cannabis - old",
      "points": [
        [
          507.77777777777777,
          218.88888888888889
        ],
        [
          502.2222222222222,
          249.25925925925924
        ],
        [
          515.1851851851851,
          257.037037037037
        ],
        [
          581.1111111111111,
          272.96296296296293
        ],
        [
          652.5925925925925,
          268.14814814814815
        ],
        [
          664.4444444444445,
          256.2962962962963
        ],
        [
          652.9629629629629,
          221.1111111111111
        ],
        [
          617.4074074074074,
          238.5185185185185
        ],
        [
          588.1481481481482,
          241.48148148148147
        ],
        [
          566.2962962962963,
          223.33333333333331
        ],
        [
          550.3703703703703,
          218.14814814814812
        ],
        [
          525.9259259259259,
          214.07407407407405
        ]
      ],
      "group_id": null,
      "description": "",
      "shape_type": "polygon",
      "flags": {},
      "mask": null
    }
  ],
  "imagePath": "20001060_20160620.tif",
  "imageHeight": 846,
  "imageWidth": 693
}
